gsim/__init__.py
gsim/gcloud.py
gsim/viz.py
gsim/common/__init__.py
gsim/common/geometry.py
gsim/common/stack/__init__.py
gsim/common/stack/extractor.py
gsim/common/stack/materials.py
gsim/common/stack/visualization.py
gsim/palace/__init__.py
gsim/palace/base.py
gsim/palace/driven.py
gsim/palace/eigenmode.py
gsim/palace/electrostatic.py
gsim/palace/mesh/__init__.py
gsim/palace/mesh/generator.py
gsim/palace/mesh/gmsh_utils.py
gsim/palace/mesh/pipeline.py
gsim/palace/models/__init__.py
gsim/palace/models/geometry.py
gsim/palace/models/mesh.py
gsim/palace/models/numerical.py
gsim/palace/models/ports.py
gsim/palace/models/problems.py
gsim/palace/models/results.py
gsim/palace/models/stack.py
gsim/palace/ports/__init__.py
gsim/palace/ports/config.py
gsim-0.0.2.dist-info/METADATA
gsim-0.0.2.dist-info/WHEEL
gsim-0.0.2.dist-info/top_level.txt
gsim-0.0.2.dist-info/RECORD
